core/__init__.py
core/asgi.py
core/settings.py
core/urls.py
core/wsgi.py
mobiska/__init__.py
mobiska/client.py
mobiska/models.py
mobiska_sdk-0.1.0.dist-info/METADATA
mobiska_sdk-0.1.0.dist-info/WHEEL
mobiska_sdk-0.1.0.dist-info/top_level.txt
mobiska_sdk-0.1.0.dist-info/RECORD
