Metadata-Version: 2.1
Name: mobiska-sdk
Version: 0.1.0
Summary: A Django-based SDK for integrating with the Mobiska Payment Gateway
Home-page: https://github.com/stimuluz/mobiska-sdk
Author: Stimuluz
Author-email: hello@stimuluz.com
License: UNKNOWN
Platform: UNKNOWN
Classifier: Development Status :: 4 - Beta
Classifier: Intended Audience :: Developers
Classifier: License :: OSI Approved :: MIT License
Classifier: Programming Language :: Python :: 3
Classifier: Programming Language :: Python :: 3.8
Classifier: Programming Language :: Python :: 3.9
Classifier: Programming Language :: Python :: 3.10
Classifier: Framework :: Django
Classifier: Framework :: Django :: 3.2
Classifier: Framework :: Django :: 4.0
Classifier: Framework :: Django :: 4.1
Classifier: Framework :: Django :: 4.2
Requires-Python: >=3.8
Requires-Dist: Django (==5.2.4)
Requires-Dist: PyYAML (==6.0.2)
Requires-Dist: asgiref (==3.9.1)
Requires-Dist: attrs (==25.3.0)
Requires-Dist: certifi (==2025.7.14)
Requires-Dist: charset-normalizer (==3.4.2)
Requires-Dist: django-environ (==0.12.0)
Requires-Dist: djangorestframework (==3.16.0)
Requires-Dist: drf-spectacular-sidecar (==2025.7.1)
Requires-Dist: drf-spectacular (==0.28.0)
Requires-Dist: idna (==3.10)
Requires-Dist: inflection (==0.5.1)
Requires-Dist: jsonschema-specifications (==2025.4.1)
Requires-Dist: jsonschema (==4.25.0)
Requires-Dist: psycopg (==3.2.9)
Requires-Dist: referencing (==0.36.2)
Requires-Dist: requests (==2.32.4)
Requires-Dist: rpds-py (==0.26.0)
Requires-Dist: sqlparse (==0.5.3)
Requires-Dist: typing-extensions (==4.14.1)
Requires-Dist: uritemplate (==4.2.0)
Requires-Dist: urllib3 (==2.5.0)
